LICENSE.txt
MANIFEST.in
README.md
setup.py
django_perfieldperms.egg-info/PKG-INFO
django_perfieldperms.egg-info/SOURCES.txt
django_perfieldperms.egg-info/dependency_links.txt
django_perfieldperms.egg-info/requires.txt
django_perfieldperms.egg-info/top_level.txt
perfieldperms/__init__.py
perfieldperms/admin.py
perfieldperms/apps.py
perfieldperms/backends.py
perfieldperms/forms.py
perfieldperms/models.py
perfieldperms/utils.py
perfieldperms/management/__init__.py
perfieldperms/management/commands/__init__.py
perfieldperms/management/commands/pfp-makeperms.py
perfieldperms/migrations/0001_initial.py
perfieldperms/migrations/0001_squashed_0002_auto_20180921_1611.py
perfieldperms/migrations/0002_auto_20180921_1611.py
perfieldperms/migrations/__init__.py
perfieldperms/static/perfieldperms/css/pfp_admin.css
perfieldperms/templates/perfieldperms/perfieldperm_manage.html
perfieldperms/templates/perfieldperms/pfp_filter_field.html
perfieldperms/templates/perfieldperms/pfp_submit_line.html
perfieldperms/templatetags/pfp_tags.py