Metadata-Version: 1.2
Name: django-perfieldperms
Version: 0.1.7
Summary: Per model field permissions for Django.
Home-page: https://gitlab.anu.edu.au/CIMS/django-perfieldperms
Author: Lincoln Smith
Author-email: lincoln.smith@anu.edu.au
License: Apache-2.0
Platform: UNKNOWN
Classifier: Programming Language :: Python
Classifier: Programming Language :: Python :: 3 :: Only
Classifier: License :: OSI Approved :: Apache Software License
Classifier: Operating System :: OS Independent
Classifier: Development Status :: 3 - Alpha
Classifier: Environment :: Web Environment
Classifier: Framework :: Django :: 1.11
Classifier: Framework :: Django :: 2.0
Classifier: Framework :: Django :: 2.1
Classifier: Intended Audience :: Developers
Classifier: Topic :: Internet :: WWW/HTTP
Classifier: Topic :: Software Development :: Libraries :: Python Modules
Requires-Python: ~=3.4
